midas_tape/__init__.py
midas_tape-0.1.0.dist-info/WHEEL
midas_tape-0.1.0.dist-info/METADATA
midas_tape-0.1.0.dist-info/RECORD
