Metadata-Version: 2.1
Name: midas-tape
Version: 0.1.0
Summary: Read MIDAS tape server files
License: BSD-3
Author: Angus Hollands
Author-email: goosey15@gmail.com
Requires-Python: >=3.7,<4.0
Classifier: License :: Other/Proprietary License
Classifier: Programming Language :: Python :: 3
Classifier: Programming Language :: Python :: 3.7
Classifier: Programming Language :: Python :: 3.8
Classifier: Programming Language :: Python :: 3.9
Requires-Dist: awkward (>=1.2.0,<2.0.0)
Requires-Dist: numpy (>=1.13.1,<2.0.0)
